{
  "card_id": "DR_5_golem",
  "name_slug": "golem",
  "display_name": "Golem",
  "card_type": "POKEMON",
  "stage": "STAGE2",
  "evolves_from": "graveler",
  "pokemon_type": "FIGHTING",
  "hp_max": 120,
  "weakness": "WATER",
  "resistance": "NONE",
  "retreat_cost": 4,
  "rules_text": "",
  "attacks": [
    {
      "name": "Rock Vengeance",
      "base_damage": 20,
      "text": "Does 20 damage plus 10 more damage for each damage counter on all of your Active Pokémon.",
      "cost_fighting": 1,
      "cost_colorless": 2,
      "effect_key": "damage_scaling",
      "effect_params": {
        "basis": "damage_counters_actives_own",
        "per_unit": 10
      }
    },
    {
      "name": "Rock Slide",
      "base_damage": 60,
      "text": "Does 20 damage to 2 of your opponent's Benched Pokémon (1 if there is only 1). (Don't apply Weakness and Resistance for Benched Pokémon.)",
      "cost_fighting": 2,
      "cost_colorless": 3
    }
  ]
}
